multipleresponsestestapi/__init__.py
multipleresponsestestapi/api_helper.py
multipleresponsestestapi/configuration.py
multipleresponsestestapi/decorators.py
multipleresponsestestapi/multipleresponsestestapi_client.py
multipleresponsestestapi/controllers/__init__.py
multipleresponsestestapi/controllers/base_controller.py
multipleresponsestestapi/controllers/send_messages_controller.py
multipleresponsestestapi/exceptions/__init__.py
multipleresponsestestapi/exceptions/api_exception.py
multipleresponsestestapi/exceptions/failure_response_model_exception.py
multipleresponsestestapi/exceptions/success_response_model_exception.py
multipleresponsestestapi/http/__init__.py
multipleresponsestestapi/http/http_call_back.py
multipleresponsestestapi/http/http_client.py
multipleresponsestestapi/http/http_method_enum.py
multipleresponsestestapi/http/http_request.py
multipleresponsestestapi/http/http_response.py
multipleresponsestestapi/http/requests_client.py
multipleresponsestestapi/models/__init__.py
multipleresponsestestapi/models/id_type.py
multipleresponsestestapi/models/multiple_message_model.py
multipleresponsestestapi/models/reason.py
multipleresponsestestapi/models/single_message_model.py
multipleresponsestestapi/utilities/__init__.py
multipleresponsestestapi/utilities/file_wrapper.py
tests/__init__.py
tests/http_response_catcher.py
tests/test_helper.py
tests/controllers/__init__.py
tests/controllers/controller_test_base.py
tests/controllers/test_send_messages_controller.py
altest_multiple_res-2.0.0.dist-info/LICENSE
altest_multiple_res-2.0.0.dist-info/METADATA
altest_multiple_res-2.0.0.dist-info/WHEEL
altest_multiple_res-2.0.0.dist-info/top_level.txt
altest_multiple_res-2.0.0.dist-info/RECORD
