Metadata-Version: 2.1
Name: altest-multiple-res
Version: 2.0.0
Summary: Python client library for Multiple Responses Test API
Home-page: https://apimatic.io
Author: APIMatic SDK Generator
Author-email: heri@little.bz
License: UNKNOWN
Platform: UNKNOWN
Requires-Dist: requests (<3.0,>=2.9.1)
Requires-Dist: jsonpickle (<1.0,>=0.7.1)
Requires-Dist: cachecontrol (<1.0,>=0.11.7)
Requires-Dist: python-dateutil (<3.0,>=2.5.3)
Requires-Dist: enum34 (>=1.1.6)
